pplite/bounding_box.pxd
pplite/polyhedron.cpython-310-darwin.so
pplite/generators.cpython-310-darwin.so
pplite/pplite_decl.pxd
pplite/intervals.pxd
pplite/linear_algebra.pxd
pplite/integer_conversions.pxd
pplite/bounding_box.cpython-310-darwin.so
pplite/integer_conversions.cpython-310-darwin.so
pplite/constraint.pxd
pplite/__init__.py
pplite/linear_algebra.cpython-310-darwin.so
pplite/constraint.cpython-310-darwin.so
pplite/generators.pxd
pplite/intervals.cpython-310-darwin.so
pplite/flint_wrap.h
pplite/polyhedron.pxd
pplite/.dylibs/libgmpxx.4.dylib
pplite/.dylibs/libpplite.5.dylib
pplite/.dylibs/libflint.21.0.dylib
pplite/.dylibs/libgmp.10.dylib
pplite/.dylibs/libmpfr.6.dylib
pplitepy-0.0.55.dist-info/RECORD
pplitepy-0.0.55.dist-info/WHEEL
pplitepy-0.0.55.dist-info/top_level.txt
pplitepy-0.0.55.dist-info/METADATA
