Metadata-Version: 2.4
Name: pplitepy
Version: 0.0.55
Summary: Python pplite wrapper
Author-email: Acadia Larsen <acadia.larsen@gmail.com>
License: GPL v3
Project-URL: Homepage, https://github.com/ComboProblem/pplitepy
Project-URL: Download, https://github.com/ComboProblem/pplitepy
Keywords: polyhedron,polytope,convex,mathematics,ppl,pplite,milp,linear-programming
Platform: any
Classifier: License :: OSI Approved :: GNU General Public License v3 (GPLv3)
Classifier: Programming Language :: C++
Classifier: Programming Language :: Python
Classifier: Development Status :: 3 - Alpha
Classifier: Operating System :: Unix
Classifier: Intended Audience :: Science/Research
Classifier: Programming Language :: Python :: 3.8
Classifier: Programming Language :: Python :: 3.9
Classifier: Programming Language :: Python :: 3.10
Classifier: Programming Language :: Python :: 3.11
Classifier: Programming Language :: Python :: 3.12
Classifier: Topic :: Scientific/Engineering :: Mathematics
Requires-Dist: cysignals
Requires-Dist: gmpy2>=2.1.0b1
Provides-Extra: doc
Requires-Dist: sphinx; extra == "doc"
